sqlite_vec_client/__init__.py
sqlite_vec_client/base.py
sqlite_vec_client/types.py
sqlite_vec_client/utils.py
sqlite_vec_client-0.1.0.dist-info/licenses/LICENSE
sqlite_vec_client-0.1.0.dist-info/METADATA
sqlite_vec_client-0.1.0.dist-info/WHEEL
sqlite_vec_client-0.1.0.dist-info/top_level.txt
sqlite_vec_client-0.1.0.dist-info/RECORD
